platform_checker/__init__.py
platform_checker/detector.py
platform_checker-0.2.2.dist-info/licenses/LICENSE
platform_checker-0.2.2.dist-info/METADATA
platform_checker-0.2.2.dist-info/WHEEL
platform_checker-0.2.2.dist-info/top_level.txt
platform_checker-0.2.2.dist-info/RECORD
