Metadata-Version: 2.4
Name: platform-checker
Version: 0.2.2
Summary: A simple package for checking the platform type.
Home-page: https://github.com/yourusername/platform_checker
Author: Aditya Sriram
Author-email: Aditya Sriram <adisriram7777@gmail.com>
License: MIT
Requires-Python: >=3.6
License-File: LICENSE
Dynamic: author
Dynamic: home-page
Dynamic: license-file
Dynamic: requires-python
